setup.py
gameforged/__bases__.py
gameforged/__init__.py
gameforged/gaming/__init__.py
gameforged/gaming/classical.py
gameforged/workshop/__init__.py
gameforged/workshop/blacksmith.py
gameforged/workshop/bookshelves.py
gameforged/workshop/rulebooks.py
gameforged-0.1.1.dist-info/LICENSE
gameforged-0.1.1.dist-info/METADATA
gameforged-0.1.1.dist-info/WHEEL
gameforged-0.1.1.dist-info/top_level.txt
gameforged-0.1.1.dist-info/RECORD
