Metadata-Version: 2.2
Name: gameforged
Version: 0.1.1
Summary: A comprehensive Python framework for game theory modeling, analysis, and simulation.
Author-email: DirtyWork Solutions Limited <gameforge@open.dirtywork.solutions>
Project-URL: Homepage, https://open.dirtywork.solutions/gameforgde
Project-URL: Documentation, https://open.dirtywork.solutions/gameforged/docs
Project-URL: Source, https://github.com/DirtyWork-Solutions/GameForge
Project-URL: Issues, https://github.com/DirtyWork-Solutions/GameForge/tree/main/.github/ISSUE_TEMPLATE
License-File: LICENSE
Requires-Dist: cachetools
Requires-Dist: pydantic
Requires-Dist: pandas
Requires-Dist: scikit-learn
Requires-Dist: numpy
Requires-Dist: scipy
Requires-Dist: pyutile
